qmk_via_api-0.5.0.dist-info/METADATA
qmk_via_api-0.5.0.dist-info/WHEEL
qmk_via_api/__init__.py
qmk_via_api/qmk_via_api.pyd
qmk_via_api-0.5.0.dist-info/RECORD
