Metadata-Version: 2.4
Name: qmk-via-api
Version: 0.5.0
Summary: VIA api implementation for QMK-based keyboards
Author: Stephan Rumswinkel
License: GPL-3.0-only
Project-URL: Source Code, https://github.com/srwi/qmk-via-api
